<?xml version="1.0" encoding="utf-8"?>

<D-Spin xmlns="http://www.dspin.de/data" version="0.4">

 <MetaData xmlns="http://www.dspin.de/data/metadata">
  <source>IMS, Uni Stuttgart</source>
 </MetaData>

 <TextCorpus xmlns="http://www.dspin.de/data/textcorpus" lang="de">
  <text>Peter aß eine Käsepizza. Sie schmeckte ihm.</text>
  <tokens charOffsets="true">
   <token ID="t1">Peter</token>
   <token ID="t2">aß</token>
   <token ID="t3">eine</token>
   <token ID="t4">Käsepizza</token>
   <token ID="t5">.</token>
   <token ID="t6">Sie</token>
   <token ID="t7">schmeckte</token>
   <token ID="t8">ihm</token>
   <token ID="t9">.</token>
  </tokens>
  <sentences charOffsets="true">
   <sentence ID="s1" start="1" end="20" tokenIDs="t1 t2 t3 t4 t5"/>
   <sentence ID="s2" start="22" end="39" tokenIDs="t6 t7 t8 t9"/>
  </sentences>
  <POStags tagset="STTS">
   <tag tokenIDs="t1">NE</tag>
   <tag tokenIDs="t2">VVFIN</tag>
   <tag tokenIDs="t3">ART</tag>
   <tag tokenIDs="t4">NE</tag>
   <tag tokenIDs="t5">$.</tag>
   <tag tokenIDs="t6">PPER</tag>
   <tag tokenIDs="t7">VVFIN</tag>
   <tag tokenIDs="t8">PPER</tag>
   <tag tokenIDs="t9">$.</tag>
  </POStags>
  <lemmas>
   <lemma tokenIDs="t1">Peter</lemma>
   <lemma tokenIDs="t2">essen</lemma>
   <lemma tokenIDs="t3">ein</lemma>
   <lemma tokenIDs="t4">Käsepizza</lemma>
   <lemma tokenIDs="t5">.</lemma>
   <lemma tokenIDs="t6">sie</lemma>
   <lemma tokenIDs="t7">schmecken</lemma>
   <lemma tokenIDs="t8">er</lemma>
   <lemma tokenIDs="t9">.</lemma>
  </lemmas>
  <morphology segmentation="true">
    <analysis tokenIDs="t4">
      <tag>
        <fs>
          <f name="cat">noun</f>
          <f name="case">acc</f>
          <f name="gender">fem</f>
          <f name="number">singular</f>
        </fs>
      </tag>
      <segmentation>
        <segment cat="noun" start="0" end="9">
          <segment type="stem" cat="noun" func="comp" start="0" end="4">
            Käse
          </segment>
          <segment type="stem" cat="noun" func="base" start="4" end="9">
            Pizza
          </segment>
        </segment>
      </segmentation>
    </analysis>
  </morphology>
  <namedEntities type="MUC1990">
    <entity class="PERSON" tokenIDs="t1"/>
  </namedEntities>
  <WordSplittings type="hyphenation">
    <split tokID="t4">2 4 7</split>
  </WordSplittings> 
  <Phonetics transcription="IPA">
    <pron tokID="t7">ʃmekən</pron>
  </Phonetics> 
  <QueryResults query="ggkk">
    <match tokenIDs="t1 t2 t3 t4">
      <key tokenIDs="t2 t4"/>
    </match>
  </QueryResults>
  <parsing tagset="Tiger">
   <parse>
    <constituent ID="c1" cat="TOP">
     <constituent ID="c2" cat="S-TOP">
      <constituent ID="c3" cat="NP-SB">
       <constituent ID="c4" cat="PN-HD-Nom.Sg">
        <constituent ID="c5" cat="NE-HD-Nom.Sg" tokenIDs="t1"/>
       </constituent>
      </constituent>
      <constituent cat="VVFIN-HD" ID="c6" tokenIDs="t2"/>
      <constituent ID="c7" cat="NP-OA">
       <constituent cat="ART-NK-Acc.Sg" ID="c8" tokenIDs="t3"/>
       <constituent cat="NN-NK-Acc.Sg" ID="c9" tokenIDs="t4"/>
      </constituent>
     </constituent>
     <constituent cat="\$." ID="c10" tokenIDs="t5"/>
    </constituent>
   </parse>
   <parse>
    <constituent ID="c11" cat="TOP">
     <constituent ID="c12" cat="S-TOP">
      <constituent ID="c13" cat="NP-SB">
       <constituent cat="PPER-HD-Nom" ID="c14" tokenIDs="t6"/>
      </constituent>
      <constituent cat="VVFIN-HD" ID="c15" tokenIDs="t7"/>
      <constituent ID="c16" cat="NP-DA">
       <constituent cat="PPER-HD-Dat" ID="c17" tokenIDs="t8"/>
      </constituent>
     </constituent>
     <constituent cat="\$." ID="c18" tokenIDs="t9"/>
    </constituent>
   </parse>
  </parsing>
  <depparsing>
   <parse>
    <dependency func="SUBJ" depIDs="t1" govIDs="t2"/>
    <dependency func="SPEC" depIDs="t3" govIDs="t4"/>
    <dependency func="OBJ" depIDs="t4" govIDs="t2"/>
   </parse>
   <parse>
    <dependency func="SUBJ" depIDs="t6" govIDs="t7"/>
    <dependency func="OBJ" depIDs="t8" govIDs="t7"/>
   </parse>
  </depparsing>
  <relations type="coreference">
   <relation refIDs="c3 c17"/>
   <relation refIDs="c7 c13"/>
  </relations>
 </TextCorpus>
</D-Spin>
